{"photos": {"total": "5", "photo": [{"ispublic": 1, "owner": "39312862@N00", "id": "6337515922", "title": "Financial District, San Francisco", "datetaken": "2005-10-07 12:14:45", "isfriend": 0, "secret": "7336f334ff", "ownername": "Eric Hunt.", "latitude": 0, "accuracy": 0, "isfamily": 0, "description": {"_content": "101 California to the left and One California in the center"}, "tags": "sanfrancisco california blue sky skyline skyscraper highrise usbank 101california onecalifornia", "farm": 7, "width_m": "500", "height_m": "334", "datetakenunknown": 0, "datetakengranularity": "0", "url_s": "https://farm7.staticflickr.com/6058/6337515922_7336f334ff_m.jpg", "longitude": 0, "server": "6058", "url_m": "https://farm7.staticflickr.com/6058/6337515922_7336f334ff.jpg", "context": 0, "height_s": "160", "width_s": "240"}, {"ispublic": 1, "owner": "13563767@N03", "id": "6297543023", "title": "11498 / axonometric city", "datetaken": "2011-06-02 18:19:44", "isfriend": 0, "secret": "212f7afaa8", "ownername": "janeland", "latitude": 0, "accuracy": 0, "isfamily": 0, "description": {"_content": ""}, "tags": "sanfrancisco architecture financialdistrict juxtaposition 94111 94105 matsonbuilding onecalifornia noncoloursincolour", "farm": 7, "width_m": "500", "height_m": "282", "datetakenunknown": 0, "datetakengranularity": "0", "url_s": "https://farm7.staticflickr.com/6237/6297543023_212f7afaa8_m.jpg", "longitude": 0, "server": "6237", "url_m": "https://farm7.staticflickr.com/6237/6297543023_212f7afaa8.jpg", "context": 0, "height_s": "135", "width_s": "240"}, {"ispublic": 1, "owner": "75712496@N00", "id": "5756036413", "title": "Stephs view", "datetaken": "2011-05-24 20:15:59", "isfriend": 0, "secret": "6f08d5c2f0", "ownername": "Ragorder.com (Mark Stanley)", "latitude": 0, "accuracy": 0, "isfamily": 0, "description": {"_content": "iPhone4 / Instagram"}, "tags": "sanfrancisco skyscraper view steph baybridge 29 iphone tiltshift onecalifornia iphone4 onecal instagram", "farm": 6, "width_m": "500", "height_m": "500", "datetakenunknown": 0, "datetakengranularity": "0", "url_s": "https://farm6.staticflickr.com/5028/5756036413_6f08d5c2f0_m.jpg", "longitude": 0, "server": "5028", "url_m": "https://farm6.staticflickr.com/5028/5756036413_6f08d5c2f0.jpg", "context": 0, "height_s": "240", "width_s": "240"}, {"ispublic": 1, "place_id": "iIt1rq9TUb1LDiek", "geo_is_public": 1, "owner": "50847591@N00", "id": "4558084988", "title": "one", "woeid": "2379855", "geo_is_friend": 0, "geo_is_contact": 0, "datetaken": "2010-04-23 08:12:58", "isfriend": 0, "secret": "535006ae85", "ownername": "bhautik joshi", "latitude": "37.793482", "accuracy": "16", "isfamily": 0, "description": {"_content": "As seen in Chinatown.\n\nPhoto taken with <a href=\"http://cow.mooh.org/2009/12/plungercam-mini-prototype.html\" rel=\"nofollow\">plungercam mini</a>."}, "tags": "onecalifornia 1california chinatown sanfrancisco california 2010 spring april2010 muni bus publictransport sf sfist downtown tiltshift realtiltshift plungercam plungercammini selectivefocus vehicle miniature", "farm": 4, "geo_is_family": 0, "width_m": "333", "height_m": "500", "datetakenunknown": "0", "datetakengranularity": "0", "url_s": "https://farm4.staticflickr.com/3280/4558084988_535006ae85_m.jpg", "longitude": "-122.406122", "server": "3280", "url_m": "https://farm4.staticflickr.com/3280/4558084988_535006ae85.jpg", "context": 0, "height_s": "240", "width_s": "160"}, {"ispublic": 1, "owner": "10250594@N07", "id": "2608887492", "title": "The One California building @ Ca st., SF,CA", "datetaken": "2008-01-09 12:31:18", "isfriend": 0, "secret": "eac360a4a2", "ownername": "AXE | Photography - Akshay P", "latitude": 0, "accuracy": 0, "isfamily": 0, "description": {"_content": "The one California building has the initials US bank at the top and stands at 134m and has 32 floors. "}, "tags": "sanfrancisco ca usbank onecalifornia", "farm": 4, "width_m": "500", "height_m": "375", "datetakenunknown": 0, "datetakengranularity": "0", "url_s": "https://farm4.staticflickr.com/3056/2608887492_eac360a4a2_m.jpg", "longitude": 0, "server": "3056", "url_m": "https://farm4.staticflickr.com/3056/2608887492_eac360a4a2.jpg", "context": 0, "height_s": "180", "width_s": "240"}], "perpage": 500, "page": 1, "pages": 1}, "stat": "ok"}